{
  "map1Path": [
    {
      "x": -32.125,
      "y": 32
    },
    {
      "x": 111.875,
      "y": 32
    },
    {
      "x": 111.875,
      "y": 96
    },
    {
      "x": 31.875,
      "y": 96
    },
    {
      "x": 31.875,
      "y": 192
    },
    {
      "x": 159.875,
      "y": 192
    },
    {
      "x": 159.875,
      "y": 256
    },
    {
      "x": 271.875,
      "y": 256
    },
    {
      "x": 271.875,
      "y": 32
    },
    {
      "x": 447.875,
      "y": 32
    },
    {
      "x": 447.875,
      "y": 352
    }
  ]
}
